Metadata-Version: 1.0
Name: bdr-spl-distributions
Version: 0.1
Summary: Gaussian distributions
Home-page: UNKNOWN
Author: bdr spl
Author-email: UNKNOWN
License: UNKNOWN
Platform: UNKNOWN
